Workbook

Sheet Cleaned data
A1: Product Code | B1: Product Name | C1: Category | D1: Supplier | E1: Cost Price (est.) | F1: Current Price | G1: Original Promo Price | H1: Competitor Price | I1: Platform | J1: `Platform Fee% | K1: Last Updated
A2: IP13-128 | B2: iPhone 13 128GB | C2: iPhone | D2: Apple Official | E2: 1850 | F2: 2199 | G2: 2099 | H2: 2088 | I2: Shopee | J2: 8 | K2: 46162
A3: SA55 | B3: Samsung Galaxy A55 | C3: Samsung | D3: Samsung MY | E3: 1350 | F3: 1699 | G3: 1599 | H3: 1588 | I3: Lazada | J3: 6 | K3: 46164
A4: IP14P-256 | B4: iPhone 14 Pro 256GB | C4: iPhone | D4: Apple Official | E4: 3250 | F4: 3899 | G4: 3699 | H4: 3750 | I4: Tiktok Shop | J4: 5 | K4: 46162
A5: S24-256 | B5: Samsung Galaxy S24 256GB | C5: Samsung | D5: Samsung MY | E5: 2450 | F5: 2999 | G5: 2799 | H5: 2850 | I5: Website | J5: 0 | K5: 46163
A6: IP15-128 | B6: iPhone 15 128GB | C6: iPhone | D6: Apple Official | E6: 3950 | F6: 4599 | G6: 4399 | H6: 4300 | I6: Shopee | J6: 8 | K6: 46162
A7: IP13-256 | B7: iPhone 13 256GB | C7: iPhone | D7: Apple Official | E7: 2000 | F7: 2399 | G7: 2199 | H7: 2250 | I7: Lazada | J7: 6 | K7: 46162
A8: SA35 | B8: Samsung Galaxy A35 | C8: Samsung | D8: Samsung MY | E8: 1150 | F8: 1399 | G8: 1299 | H8: 1250 | I8: Shopee | J8: 8 | K8: 46164
A9: IP14-128 | B9: iPhone 14 128GB | C9: iPhone | D9: Apple Official | E9: 2750 | F9: 3299 | G9: 3099 | H9: 3150 | I9: Tiktok Shop | J9: 5 | K9: 46162
A10: S23FE | B10: Samsung Galaxy S23 FE | C10: Samsung | D10: Samsung MY | E10: 2050 | F10: 2499 | G10: 2299 | H10: 2350 | I10: Lazada | J10: 6 | K10: 46163
A11: IP15P-256 | B11: iPhone 15 Pro 256GB | C11: iPhone | D11: Apple Official | E11: 4450 | F11: 5299 | G11: 4999 | H11: 5050 | I11: Website | J11: 0 | K11: 46162
A12: IP16-128 | B12: iPhone 16 128GB | C12: iPhone | D12: Apple Official | E12: 4750 | F12: 5399 | G12: 5099 | H12: 5150 | I12: Shopee | J12: 8 | K12: 46162
A13: SA56 | B13: Samsung Galaxy A56 | C13: Samsung | D13: Samsung MY | E13: 1550 | F13: 1899 | G13: 1799 | H13: 1750 | I13: Lazada | J13: 6 | K13: 46163
... A31: S24-512 | B31: Samsung Galaxy S24 512GB | C31: Samsung | D31: Samsung MY | E31: 2950 | F31: 3799 | G31: 3599 | H31: 3650 | I31: Shopee | J31: 8 | K31: 46162

Sheet Working sheet
A1: Product Code | B1: Product | C1: Current Price (RM) | D1: Promo Price (RM) | E1: Competitor Price (RM) | F1: Platform | G1: Platform Fee (%) | H1: Revenue After Fee (RM) | I1: Cost Price (RM) | J1: Profit (RM) | K1: Margin (%) | L1: vs Competitor | M1: Status | N1: Risk Level
A2: IP13-128 | B2: iPhone 13 128GB | C2: 2199 | D2: 2099 | E2: 2088 | F2: Shopee | G2: 8 | H2: =D2*(1-G2/100) -> 1931.08 | I2: =VLOOKUP(A2,'Cleaned data'!A1:K31, 5, FALSE) -> 1850 | J2: =H2-I2 -> 81.08 | K2: =J2/H2 -> 0.041986867 | L2: =D2-E2 -> 11 | M2: =IF(J2<0,"LOSS RISK",IF(K2<0.08,"Tight Margin","OK")) -> Tight Margin | N2: =IF('Working sheet'!M2:M31 = "LOSS RISK", "CRITICAL",IF('Working sheet'!K2:K31 <0.02,"High Risk",IF('Working sheet'!K2:K31<0.05,"Medium", IF('Working sheet'!K2:K31>0.05,"Low")))) -> Medium
A3: SA55 | B3: Samsung Galaxy A55 | C3: 1699 | D3: 1599 | E3: 1588 | F3: Lazada | G3: 6 | H3: =D3*(1-G3/100) -> 1503.06 | I3: =VLOOKUP(A3,'Cleaned data'!A2:K32, 5, FALSE) -> 1350 | J3: =H3-I3 -> 153.06 | K3: =J3/H3 -> 0.10183226 | L3: =D3-E3 -> 11 | M3: =IF(J3<0,"LOSS RISK",IF(K3<0.08,"Tight Margin","OK")) -> OK | N3: =IF('Working sheet'!M3:M32 = "LOSS RISK", "CRITICAL",IF('Working sheet'!K3:K32 <0.02,"High Risk",IF('Working sheet'!K3:K32<0.05,"Medium", IF('Working sheet'!K3:K32>0.05,"Low")))) -> Low
A4: IP14P-256 | B4: iPhone 14 Pro 256GB | C4: 3899 | D4: 3699 | E4: 3750 | F4: Tiktok Shop | G4: 5 | H4: =D4*(1-G4/100) -> 3514.05 | I4: =VLOOKUP(A4,'Cleaned data'!A3:K33, 5, FALSE) -> 3250 | J4: =H4-I4 -> 264.05 | K4: =J4/H4 -> 0.075141219 | L4: =D4-E4 -> -51 | M4: =IF(J4<0,"LOSS RISK",IF(K4<0.08,"Tight Margin","OK")) -> Tight Margin | N4: =IF('Working sheet'!M4:M33 = "LOSS RISK", "CRITICAL",IF('Working sheet'!K4:K33 <0.02,"High Risk",IF('Working sheet'!K4:K33<0.05,"Medium", IF('Working sheet'!K4:K33>0.05,"Low")))) -> Low
A5: S24-256 | B5: Samsung Galaxy S24 256GB | C5: 2999 | D5: 2799 | E5: 2850 | F5: Website | G5: 0 | H5: =D5*(1-G5/100) -> 2799 | I5: =VLOOKUP(A5,'Cleaned data'!A4:K34, 5, FALSE) -> 2450 | J5: =H5-I5 -> 349 | K5: =J5/H5 -> 0.12468739 | L5: =D5-E5 -> -51 | M5: =IF(J5<0,"LOSS RISK",IF(K5<0.08,"Tight Margin","OK")) -> OK | N5: =IF('Working sheet'!M5:M34 = "LOSS RISK", "CRITICAL",IF('Working sheet'!K5:K34 <0.02,"High Risk",IF('Working sheet'!K5:K34<0.05,"Medium", IF('Working sheet'!K5:K34>0.05,"Low")))) -> Low
A6: IP15-128 | B6: iPhone 15 128GB | C6: 4599 | D6: 4399 | E6: 4300 | F6: Shopee | G6: 8 | H6: =D6*(1-G6/100) -> 4047.08 | I6: =VLOOKUP(A6,'Cleaned data'!A5:K35, 5, FALSE) -> 3950 | J6: =H6-I6 -> 97.08 | K6: =J6/H6 -> 0.023987665 | L6: =D6-E6 -> 99 | M6: =IF(J6<0,"LOSS RISK",IF(K6<0.08,"Tight Margin","OK")) -> Tight Margin | N6: =IF('Working sheet'!M6:M35 = "LOSS RISK", "CRITICAL",IF('Working sheet'!K6:K35 <0.02,"High Risk",IF('Working sheet'!K6:K35<0.05,"Medium", IF('Working sheet'!K6:K35>0.05,"Low")))) -> Medium
A7: IP13-256 | B7: iPhone 13 256GB | C7: 2399 | D7: 2199 | E7: 2250 | F7: Lazada | G7: 6 | H7: =D7*(1-G7/100) -> 2067.06 | I7: =VLOOKUP(A7,'Cleaned data'!A6:K36, 5, FALSE) -> 2000 | J7: =H7-I7 -> 67.06 | K7: =J7/H7 -> 0.032442213 | L7: =D7-E7 -> -51 | M7: =IF(J7<0,"LOSS RISK",IF(K7<0.08,"Tight Margin","OK")) -> Tight Margin | N7: =IF('Working sheet'!M7:M36 = "LOSS RISK", "CRITICAL",IF('Working sheet'!K7:K36 <0.02,"High Risk",IF('Working sheet'!K7:K36<0.05,"Medium", IF('Working sheet'!K7:K36>0.05,"Low")))) -> Medium
A8: SA35 | B8: Samsung Galaxy A35 | C8: 1399 | D8: 1299 | E8: 1250 | F8: Shopee | G8: 8 | H8: =D8*(1-G8/100) -> 1195.08 | I8: =VLOOKUP(A8,'Cleaned data'!A7:K37, 5, FALSE) -> 1150 | J8: =H8-I8 -> 45.08 | K8: =J8/H8 -> 0.037721324 | L8: =D8-E8 -> 49 | M8: =IF(J8<0,"LOSS RISK",IF(K8<0.08,"Tight Margin","OK")) -> Tight Margin | N8: =IF('Working sheet'!M8:M37 = "LOSS RISK", "CRITICAL",IF('Working sheet'!K8:K37 <0.02,"High Risk",IF('Working sheet'!K8:K37<0.05,"Medium", IF('Working sheet'!K8:K37>0.05,"Low")))) -> Medium
A9: IP14-128 | B9: iPhone 14 128GB | C9: 3299 | D9: 3099 | E9: 3150 | F9: Tiktok Shop | G9: 5 | H9: =D9*(1-G9/100) -> 2944.05 | I9: =VLOOKUP(A9,'Cleaned data'!A8:K38, 5, FALSE) -> 2750 | J9: =H9-I9 -> 194.05 | K9: =J9/H9 -> 0.065912603 | L9: =D9-E9 -> -51 | M9: =IF(J9<0,"LOSS RISK",IF(K9<0.08,"Tight Margin","OK")) -> Tight Margin | N9: =IF('Working sheet'!M9:M38 = "LOSS RISK", "CRITICAL",IF('Working sheet'!K9:K38 <0.02,"High Risk",IF('Working sheet'!K9:K38<0.05,"Medium", IF('Working sheet'!K9:K38>0.05,"Low")))) -> Low
A10: S23FE | B10: Samsung Galaxy S23 FE | C10: 2499 | D10: 2299 | E10: 2350 | F10: Lazada | G10: 6 | H10: =D10*(1-G10/100) -> 2161.06 | I10: =VLOOKUP(A10,'Cleaned data'!A9:K39, 5, FALSE) -> 2050 | J10: =H10-I10 -> 111.06 | K10: =J10/H10 -> 0.051391447 | L10: =D10-E10 -> -51 | M10: =IF(J10<0,"LOSS RISK",IF(K10<0.08,"Tight Margin","OK")) -> Tight Margin | N10: =IF('Working sheet'!M10:M39 = "LOSS RISK", "CRITICAL",IF('Working sheet'!K10:K39 <0.02,"High Risk",IF('Working sheet'!K10:K39<0.05,"Medium", IF('Working sheet'!K10:K39>0.05,"Low")))) -> Low
A11: IP15P-256 | B11: iPhone 15 Pro 256GB | C11: 5299 | D11: 4999 | E11: 5050 | F11: Website | G11: 0 | H11: =D11*(1-G11/100) -> 4999 | I11: =VLOOKUP(A11,'Cleaned data'!A10:K40, 5, FALSE) -> 4450 | J11: =H11-I11 -> 549 | K11: =J11/H11 -> 0.10982196 | L11: =D11-E11 -> -51 | M11: =IF(J11<0,"LOSS RISK",IF(K11<0.08,"Tight Margin","OK")) -> OK | N11: =IF('Working sheet'!M11:M40 = "LOSS RISK", "CRITICAL",IF('Working sheet'!K11:K40 <0.02,"High Risk",IF('Working sheet'!K11:K40<0.05,"Medium", IF('Working sheet'!K11:K40>0.05,"Low")))) -> Low
A12: IP16-128 | B12: iPhone 16 128GB | C12: 5399 | D12: 5099 | E12: 5150 | F12: Shopee | G12: 8 | H12: =D12*(1-G12/100) -> 4691.08 | I12: =VLOOKUP(A12,'Cleaned data'!A11:K41, 5, FALSE) -> 4750 | J12: =H12-I12 -> -58.92 | K12: =J12/H12 -> -0.012560008 | L12: =D12-E12 -> -51 | M12: =IF(J12<0,"LOSS RISK",IF(K12<0.08,"Tight Margin","OK")) -> LOSS RISK | N12: =IF('Working sheet'!M12:M41 = "LOSS RISK", "CRITICAL",IF('Working sheet'!K12:K41 <0.02,"High Risk",IF('Working sheet'!K12:K41<0.05,"Medium", IF('Working sheet'!K12:K41>0.05,"Low")))) -> CRITICAL
A13: SA56 | B13: Samsung Galaxy A56 | C13: 1899 | D13: 1799 | E13: 1750 | F13: Lazada | G13: 6 | H13: =D13*(1-G13/100) -> 1691.06 | I13: =VLOOKUP(A13,'Cleaned data'!A12:K42, 5, FALSE) -> 1550 | J13: =H13-I13 -> 141.06 | K13: =J13/H13 -> 0.083415136 | L13: =D13-E13 -> 49 | M13: =IF(J13<0,"LOSS RISK",IF(K13<0.08,"Tight Margin","OK")) -> OK | N13: =IF('Working sheet'!M13:M42 = "LOSS RISK", "CRITICAL",IF('Working sheet'!K13:K42 <0.02,"High Risk",IF('Working sheet'!K13:K42<0.05,"Medium", IF('Working sheet'!K13:K42>0.05,"Low")))) -> Low
... A31: S24-512 | B31: Samsung Galaxy S24 512GB | C31: 3799 | D31: 3599 | E31: 3650 | F31: Shopee | G31: 8 | H31: =D31*(1-G31/100) -> 3311.08 | I31: =VLOOKUP(A31,'Cleaned data'!A30:K60, 5, FALSE) -> 2950 | J31: =H31-I31 -> 361.08 | K31: =J31/H31 -> 0.10905203 | L31: =D31-E31 -> -51 | M31: =IF(J31<0,"LOSS RISK",IF(K31<0.08,"Tight Margin","OK")) -> OK | N31: =IF('Working sheet'!M31:M60 = "LOSS RISK", "CRITICAL",IF('Working sheet'!K31:K60 <0.02,"High Risk",IF('Working sheet'!K31:K60<0.05,"Medium", IF('Working sheet'!K31:K60>0.05,"Low")))) -> Low

Sheet Sheet2
A1: Product Code | B1: Product | C1: Current Price (RM) | D1: Promo Price (RM) | E1: Competitor Price (RM) | F1: Platform | G1: Platform Fee (%) | H1: Revenue After Fee (RM) | I1: Cost Price (RM) | J1: Profit (RM) | K1: Margin (%) | L1: vs Competitor | M1: Status | N1: Risk Level
A2: IP13-128 | B2: iPhone 13 128GB | C2: 2199 | D2: 2099 | E2: 2088 | F2: Shopee | G2: 8 | H2: 1931.08 | I2: 1850 | J2: 81.08 | K2: 0.041986867 | L2: 11 | M2: Tight Margin | N2: Medium
A3: SA55 | B3: Samsung Galaxy A55 | C3: 1699 | D3: 1599 | E3: 1588 | F3: Lazada | G3: 6 | H3: 1503.06 | I3: 1350 | J3: 153.06 | K3: 0.10183226 | L3: 11 | M3: OK | N3: Low
A4: IP14P-256 | B4: iPhone 14 Pro 256GB | C4: 3899 | D4: 3699 | E4: 3750 | F4: Tiktok Shop | G4: 5 | H4: 3514.05 | I4: 3250 | J4: 264.05 | K4: 0.075141219 | L4: -51 | M4: Tight Margin | N4: Low
A5: S24-256 | B5: Samsung Galaxy S24 256GB | C5: 2999 | D5: 2799 | E5: 2850 | F5: Website | G5: 0 | H5: 2799 | I5: 2450 | J5: 349 | K5: 0.12468739 | L5: -51 | M5: OK | N5: Low
A6: IP15-128 | B6: iPhone 15 128GB | C6: 4599 | D6: 4399 | E6: 4300 | F6: Shopee | G6: 8 | H6: 4047.08 | I6: 3950 | J6: 97.08 | K6: 0.023987665 | L6: 99 | M6: Tight Margin | N6: Medium
A7: IP13-256 | B7: iPhone 13 256GB | C7: 2399 | D7: 2199 | E7: 2250 | F7: Lazada | G7: 6 | H7: 2067.06 | I7: 2000 | J7: 67.06 | K7: 0.032442213 | L7: -51 | M7: Tight Margin | N7: Medium
A8: SA35 | B8: Samsung Galaxy A35 | C8: 1399 | D8: 1299 | E8: 1250 | F8: Shopee | G8: 8 | H8: 1195.08 | I8: 1150 | J8: 45.08 | K8: 0.037721324 | L8: 49 | M8: Tight Margin | N8: Medium
A9: IP14-128 | B9: iPhone 14 128GB | C9: 3299 | D9: 3099 | E9: 3150 | F9: Tiktok Shop | G9: 5 | H9: 2944.05 | I9: 2750 | J9: 194.05 | K9: 0.065912603 | L9: -51 | M9: Tight Margin | N9: Low
A10: S23FE | B10: Samsung Galaxy S23 FE | C10: 2499 | D10: 2299 | E10: 2350 | F10: Lazada | G10: 6 | H10: 2161.06 | I10: 2050 | J10: 111.06 | K10: 0.051391447 | L10: -51 | M10: Tight Margin | N10: Low
A11: IP15P-256 | B11: iPhone 15 Pro 256GB | C11: 5299 | D11: 4999 | E11: 5050 | F11: Website | G11: 0 | H11: 4999 | I11: 4450 | J11: 549 | K11: 0.10982196 | L11: -51 | M11: OK | N11: Low
A12: IP16-128 | B12: iPhone 16 128GB | C12: 5399 | D12: 5099 | E12: 5150 | F12: Shopee | G12: 8 | H12: 4691.08 | I12: 4750 | J12: -58.92 | K12: -0.012560008 | L12: -51 | M12: LOSS RISK | N12: CRITICAL
A13: SA56 | B13: Samsung Galaxy A56 | C13: 1899 | D13: 1799 | E13: 1750 | F13: Lazada | G13: 6 | H13: 1691.06 | I13: 1550 | J13: 141.06 | K13: 0.083415136 | L13: 49 | M13: OK | N13: Low
... A31: S24-512 | B31: Samsung Galaxy S24 512GB | C31: 3799 | D31: 3599 | E31: 3650 | F31: Shopee | G31: 8 | H31: 3311.08 | I31: 2950 | J31: 361.08 | K31: 0.10905203 | L31: -51 | M31: OK | N31: Low

Sheet Sheet3
A1: Product Code | B1: Product | C1: Current Price (RM) | D1: Promo Price (RM) | E1: Competitor Price (RM) | F1: Platform | G1: Platform Fee (%) | H1: Revenue After Fee (RM) | I1: Cost Price (RM) | J1: Profit (RM) | K1: Margin (%) | L1: vs Competitor | M1: Status | N1: Risk Level
A2: IP13-128 | B2: iPhone 13 128GB | C2: 2199 | D2: 2099 | E2: 2088 | F2: Shopee | G2: 8 | H2: 1931.08 | I2: 1850 | J2: 81.08 | K2: 0.041986867 | L2: 11 | M2: Tight Margin | N2: Medium
A3: SA55 | B3: Samsung Galaxy A55 | C3: 1699 | D3: 1599 | E3: 1588 | F3: Lazada | G3: 6 | H3: 1503.06 | I3: 1350 | J3: 153.06 | K3: 0.10183226 | L3: 11 | M3: OK | N3: Low
A4: IP14P-256 | B4: iPhone 14 Pro 256GB | C4: 3899 | D4: 3699 | E4: 3750 | F4: Tiktok Shop | G4: 5 | H4: 3514.05 | I4: 3250 | J4: 264.05 | K4: 0.075141219 | L4: -51 | M4: Tight Margin | N4: Low
A5: S24-256 | B5: Samsung Galaxy S24 256GB | C5: 2999 | D5: 2799 | E5: 2850 | F5: Website | G5: 0 | H5: 2799 | I5: 2450 | J5: 349 | K5: 0.12468739 | L5: -51 | M5: OK | N5: Low
A6: IP15-128 | B6: iPhone 15 128GB | C6: 4599 | D6: 4399 | E6: 4300 | F6: Shopee | G6: 8 | H6: 4047.08 | I6: 3950 | J6: 97.08 | K6: 0.023987665 | L6: 99 | M6: Tight Margin | N6: Medium
A7: IP13-256 | B7: iPhone 13 256GB | C7: 2399 | D7: 2199 | E7: 2250 | F7: Lazada | G7: 6 | H7: 2067.06 | I7: 2000 | J7: 67.06 | K7: 0.032442213 | L7: -51 | M7: Tight Margin | N7: Medium
A8: SA35 | B8: Samsung Galaxy A35 | C8: 1399 | D8: 1299 | E8: 1250 | F8: Shopee | G8: 8 | H8: 1195.08 | I8: 1150 | J8: 45.08 | K8: 0.037721324 | L8: 49 | M8: Tight Margin | N8: Medium
A9: IP14-128 | B9: iPhone 14 128GB | C9: 3299 | D9: 3099 | E9: 3150 | F9: Tiktok Shop | G9: 5 | H9: 2944.05 | I9: 2750 | J9: 194.05 | K9: 0.065912603 | L9: -51 | M9: Tight Margin | N9: Low
A10: S23FE | B10: Samsung Galaxy S23 FE | C10: 2499 | D10: 2299 | E10: 2350 | F10: Lazada | G10: 6 | H10: 2161.06 | I10: 2050 | J10: 111.06 | K10: 0.051391447 | L10: -51 | M10: Tight Margin | N10: Low
A11: IP15P-256 | B11: iPhone 15 Pro 256GB | C11: 5299 | D11: 4999 | E11: 5050 | F11: Website | G11: 0 | H11: 4999 | I11: 4450 | J11: 549 | K11: 0.10982196 | L11: -51 | M11: OK | N11: Low
A12: IP16-128 | B12: iPhone 16 128GB | C12: 5399 | D12: 5099 | E12: 5150 | F12: Shopee | G12: 8 | H12: 4691.08 | I12: 4750 | J12: -58.92 | K12: -0.012560008 | L12: -51 | M12: LOSS RISK | N12: CRITICAL
A13: SA56 | B13: Samsung Galaxy A56 | C13: 1899 | D13: 1799 | E13: 1750 | F13: Lazada | G13: 6 | H13: 1691.06 | I13: 1550 | J13: 141.06 | K13: 0.083415136 | L13: 49 | M13: OK | N13: Low
... A31: S24-512 | B31: Samsung Galaxy S24 512GB | C31: 3799 | D31: 3599 | E31: 3650 | F31: Shopee | G31: 8 | H31: 3311.08 | I31: 2950 | J31: 361.08 | K31: 0.10905203 | L31: -51 | M31: OK | N31: Low

Sheet Sheet4
A1: Product Code | B1: Product | C1: Current Price (RM) | D1: Promo Price (RM) | E1: Competitor Price (RM) | F1: Platform | G1: Platform Fee (%) | H1: Revenue After Fee (RM) | I1: Cost Price (RM) | J1: Profit (RM) | K1: Margin (%) | L1: vs Competitor | M1: Status | N1: Risk Level
A2: IP13-128 | B2: iPhone 13 128GB | C2: 2199 | D2: 2099 | E2: 2088 | F2: Shopee | G2: 8 | H2: 1931.08 | I2: 1850 | J2: 81.08 | K2: 0.041986867 | L2: 11 | M2: Tight Margin | N2: Medium
A3: SA55 | B3: Samsung Galaxy A55 | C3: 1699 | D3: 1599 | E3: 1588 | F3: Lazada | G3: 6 | H3: 1503.06 | I3: 1350 | J3: 153.06 | K3: 0.10183226 | L3: 11 | M3: OK | N3: Low
A4: IP14P-256 | B4: iPhone 14 Pro 256GB | C4: 3899 | D4: 3699 | E4: 3750 | F4: Tiktok Shop | G4: 5 | H4: 3514.05 | I4: 3250 | J4: 264.05 | K4: 0.075141219 | L4: -51 | M4: Tight Margin | N4: Low
A5: S24-256 | B5: Samsung Galaxy S24 256GB | C5: 2999 | D5: 2799 | E5: 2850 | F5: Website | G5: 0 | H5: 2799 | I5: 2450 | J5: 349 | K5: 0.12468739 | L5: -51 | M5: OK | N5: Low
A6: IP15-128 | B6: iPhone 15 128GB | C6: 4599 | D6: 4399 | E6: 4300 | F6: Shopee | G6: 8 | H6: 4047.08 | I6: 3950 | J6: 97.08 | K6: 0.023987665 | L6: 99 | M6: Tight Margin | N6: Medium
A7: IP13-256 | B7: iPhone 13 256GB | C7: 2399 | D7: 2199 | E7: 2250 | F7: Lazada | G7: 6 | H7: 2067.06 | I7: 2000 | J7: 67.06 | K7: 0.032442213 | L7: -51 | M7: Tight Margin | N7: Medium
A8: SA35 | B8: Samsung Galaxy A35 | C8: 1399 | D8: 1299 | E8: 1250 | F8: Shopee | G8: 8 | H8: 1195.08 | I8: 1150 | J8: 45.08 | K8: 0.037721324 | L8: 49 | M8: Tight Margin | N8: Medium
A9: IP14-128 | B9: iPhone 14 128GB | C9: 3299 | D9: 3099 | E9: 3150 | F9: Tiktok Shop | G9: 5 | H9: 2944.05 | I9: 2750 | J9: 194.05 | K9: 0.065912603 | L9: -51 | M9: Tight Margin | N9: Low
A10: S23FE | B10: Samsung Galaxy S23 FE | C10: 2499 | D10: 2299 | E10: 2350 | F10: Lazada | G10: 6 | H10: 2161.06 | I10: 2050 | J10: 111.06 | K10: 0.051391447 | L10: -51 | M10: Tight Margin | N10: Low
A11: IP15P-256 | B11: iPhone 15 Pro 256GB | C11: 5299 | D11: 4999 | E11: 5050 | F11: Website | G11: 0 | H11: 4999 | I11: 4450 | J11: 549 | K11: 0.10982196 | L11: -51 | M11: OK | N11: Low
A12: IP16-128 | B12: iPhone 16 128GB | C12: 5399 | D12: 5099 | E12: 5150 | F12: Shopee | G12: 8 | H12: 4691.08 | I12: 4750 | J12: -58.92 | K12: -0.012560008 | L12: -51 | M12: LOSS RISK | N12: CRITICAL
A13: SA56 | B13: Samsung Galaxy A56 | C13: 1899 | D13: 1799 | E13: 1750 | F13: Lazada | G13: 6 | H13: 1691.06 | I13: 1550 | J13: 141.06 | K13: 0.083415136 | L13: 49 | M13: OK | N13: Low
... A31: S24-512 | B31: Samsung Galaxy S24 512GB | C31: 3799 | D31: 3599 | E31: 3650 | F31: Shopee | G31: 8 | H31: 3311.08 | I31: 2950 | J31: 361.08 | K31: 0.10905203 | L31: -51 | M31: OK | N31: Low

Sheet Sheet5
A1: Product Code | B1: Product | C1: Current Price (RM) | D1: Promo Price (RM) | E1: Competitor Price (RM) | F1: Platform | G1: Platform Fee (%) | H1: Revenue After Fee (RM) | I1: Cost Price (RM) | J1: Profit (RM) | K1: Margin (%) | L1: vs Competitor | M1: Status | N1: Risk Level
A2: IP13-128 | B2: iPhone 13 128GB | C2: 2199 | D2: 2099 | E2: 2088 | F2: Shopee | G2: 8 | H2: 1931.08 | I2: 1850 | J2: 81.08 | K2: 0.041986867 | L2: 11 | M2: Tight Margin | N2: Medium
A3: IP16P-512 | B3: iPhone 16 Pro 512GB | C3: 6799 | D3: 6499 | E3: 6550 | F3: Tiktok Shop | G3: 5 | H3: 6174.05 | I3: 6150 | J3: 24.05 | K3: 0.0038953361 | L3: -51 | M3: Tight Margin | N3: High Risk
A4: IP14P-256 | B4: iPhone 14 Pro 256GB | C4: 3899 | D4: 3699 | E4: 3750 | F4: Tiktok Shop | G4: 5 | H4: 3514.05 | I4: 3250 | J4: 264.05 | K4: 0.075141219 | L4: -51 | M4: Tight Margin | N4: Low
A5: IP15-512 | B5: iPhone 15 512GB | C5: 5299 | D5: 5099 | E5: 5150 | F5: Shopee | G5: 8 | H5: 4691.08 | I5: 4650 | J5: 41.08 | K5: 0.0087570453 | L5: -51 | M5: Tight Margin | N5: High Risk
A6: IP15-128 | B6: iPhone 15 128GB | C6: 4599 | D6: 4399 | E6: 4300 | F6: Shopee | G6: 8 | H6: 4047.08 | I6: 3950 | J6: 97.08 | K6: 0.023987665 | L6: 99 | M6: Tight Margin | N6: Medium
A7: IP13-256 | B7: iPhone 13 256GB | C7: 2399 | D7: 2199 | E7: 2250 | F7: Lazada | G7: 6 | H7: 2067.06 | I7: 2000 | J7: 67.06 | K7: 0.032442213 | L7: -51 | M7: Tight Margin | N7: Medium
A8: SA35 | B8: Samsung Galaxy A35 | C8: 1399 | D8: 1299 | E8: 1250 | F8: Shopee | G8: 8 | H8: 1195.08 | I8: 1150 | J8: 45.08 | K8: 0.037721324 | L8: 49 | M8: Tight Margin | N8: Medium
A9: IP14-128 | B9: iPhone 14 128GB | C9: 3299 | D9: 3099 | E9: 3150 | F9: Tiktok Shop | G9: 5 | H9: 2944.05 | I9: 2750 | J9: 194.05 | K9: 0.065912603 | L9: -51 | M9: Tight Margin | N9: Low
A10: S23FE | B10: Samsung Galaxy S23 FE | C10: 2499 | D10: 2299 | E10: 2350 | F10: Lazada | G10: 6 | H10: 2161.06 | I10: 2050 | J10: 111.06 | K10: 0.051391447 | L10: -51 | M10: Tight Margin | N10: Low
A11: IP14-256 | B11: iPhone 14 256GB | C11: 3599 | D11: 3399 | E11: 3450 | F11: Lazada | G11: 6 | H11: 3195.06 | I11: 2950 | J11: 245.06 | K11: 0.076699655 | L11: -51 | M11: Tight Margin | N11: Low
A12: IP16-128 | B12: iPhone 16 128GB | C12: 5399 | D12: 5099 | E12: 5150 | F12: Shopee | G12: 8 | H12: 4691.08 | I12: 4750 | J12: -58.92 | K12: -0.012560008 | L12: -51 | M12: LOSS RISK | N12: CRITICAL
A13: IP16-256 | B13: iPhone 16 256GB | C13: 5799 | D13: 5499 | E13: 5550 | F13: Tiktok Shop | G13: 5 | H13: 5224.05 | I13: 5150 | J13: 74.05 | K13: 0.014174826 | L13: -51 | M13: Tight Margin | N13: High Risk
... A19: S23-256 | B19: Samsung Galaxy S23 256GB | C19: 3299 | D19: 3099 | E19: 3120 | F19: Shopee | G19: 8 | H19: 2851.08 | I19: 2650 | J19: 201.08 | K19: 0.07052766 | L19: -21 | M19: Tight Margin | N19: Low

Sheet Dashboard
A1: KPI Summary
A3: KPI | B3: Value
A4: Total Products | B4: =COUNTA('Cleaned data'!A2:A31) -> 30
A5: Highest Margin | B5: =MAX('Working sheet'!K2:K31) -> 0.16611074
A6: Average Margin | B6: =AVERAGE('Working sheet'!K2:K31) -> 0.064855156
A7: Lowest Margin | B7: =MIN('Working sheet'!K2:K31) -> -0.013990985
A8: Products at Risk (<5%) | B8: =COUNTIF('Working sheet'!K2:K31,"<0.05") -> 12
A9: Loss Risk Product | B9: =COUNTIF('Working sheet'!M2:M31,"LOSS RISK") -> 2
A11: Products at risk
A12: Product Code | B12: Product | C12: Platform | D12: Margin | E12: Status | F12: Risk Level
A13: IP16-128 | B13: iPhone 16 128GB | C13: Shopee | D13: -0.012560008 | E13: LOSS RISK | F13: CRITICAL
A14: IP15-256 | B14: iPhone 15 256GB | C14: Shopee | D14: 0.016904614 | E14: Tight Margin | F14: High Risk
A15: IP16P-256 | B15: iPhone 16 Pro 256GB | C15: TikTok Shop | D15: 0.0086066976 | E15: Tight Margin | F15: High Risk
A16: IP15P-512 | B16: iPhone 15 Pro 512GB | C16: Shopee | D16: -0.013990985 | E16: LOSS RISK | F16: CRITICAL
A17: IP16-256 | B17: iPhone 16 256GB | C17: TikTok Shop | D17: 0.014174826 | E17: Tight Margin | F17: High Risk
A18: IP15-512 | B18: iPhone 15 512GB | C18: Shopee | D18: 0.0087570453 | E18: Tight Margin | F18: High Risk
A19: IP16P-512 | B19: iPhone 16 Pro 512GB | C19: TikTok Shop | D19: 0.0038953361 | E19: Tight Margin | F19: High Risk
A22: Quick Insights
A23: 2 products are currently in Loss Risk. Immediate price review needed.
A24: 12 out of 30 products (40%) have very low margins (<5%).
A25: Shopee has the most aggressive pricing but also the highest risk due to 8% fees.
A28: Platform performance
A29: Platform | B29: Average Margin (%)
A30: Website | B30: 0.12745799
A31: Lazada | B31: 0.079252043
A32: Tiktok Shop | B32: 0.038400537
A33: Shopee | B33: 0.036469309
A34: Grand Total | B34: 0.064855156
A69: Product | B69: Platform | C69: Margin % | D69: Status | E69: Risk Level
A70: iPhone 15 128GB | B70: Shopee | C70: 0.024 | D70: Tight Margin | E70: High
A71: iPhone 13 128GB | B71: Shopee | C71: 0.042 | D71: Tight Margin | E71: Medium
A72: iPhone 13 256GB | B72: Lazada | C72: 0.032 | D72: Tight Margin | E72: Medium
A74: Quick Insights
A75: 3 out of 6 products have tight margins after platform fees
A76: Website gives significantly better profitability
